README.md
setup.py
code_sources/GUI/okftools.py
code_sources/kernel/Makefile
code_sources/kernel/netlink_kernel.c
code_sources/user/clean_log/CMakeLists.txt
code_sources/user/clean_log/clean_log.c
code_sources/user/log_control/CMakeLists.txt
code_sources/user/log_control/log_control.c
code_sources/user/receive message/CMakeLists.txt
code_sources/user/receive message/recv_msg_from_kernel.c
code_sources/user/send message/CMakeLists.txt
code_sources/user/send message/send_msg_to_kernel.c
code_sources/user/send_control_path/CMakeLists.txt
code_sources/user/send_control_path/send_control_path.c
docs/okftools.png
docs/pip.png
docs/pyinstaller.png
docs/requirements.txt
docs/setup.png
docs/show.png
okftools/log.txt
okftools/okftools_setup.py
okftools.egg-info/PKG-INFO
okftools.egg-info/SOURCES.txt
okftools.egg-info/dependency_links.txt
okftools.egg-info/requires.txt
okftools.egg-info/top_level.txt
okftools/GUI/okftools.py
okftools/netlink_kernel/Makefile
okftools/netlink_kernel/netlink_kernel.c
okftools/user/clean_log/CMakeLists.txt
okftools/user/clean_log/clean_log.c
okftools/user/log_control/CMakeLists.txt
okftools/user/log_control/log_control.c
okftools/user/receive message/CMakeLists.txt
okftools/user/receive message/recv_msg_from_kernel.c
okftools/user/send message/CMakeLists.txt
okftools/user/send message/send_msg_to_kernel.c
okftools/user/send_control_path/CMakeLists.txt
okftools/user/send_control_path/send_control_path.c
tests/test_make_gui.py
tests/test_okftools.py