Metadata-Version: 2.1
Name: okftools
Version: 0.1.0
Summary: okftools to achieve overloading kernel function under Linux 5.19
Home-page: https://github.com/heatingma/NIS3302-okftools
Author: heatingma  qigu  cfg554  halsayxi  sora
License: Mulan PSL v2
Classifier: License :: OSI Approved :: Mulan Permissive Software License v2 (MulanPSL-2.0)
Classifier: Programming Language :: Python :: 3 :: Only
Classifier: Operating System :: POSIX :: Linux
Requires-Python: >=3.7
